UrlPermission/__init__.py
UrlPermission/UrlPermissions/__init__.py
UrlPermission/UrlPermissions/asgi.py
UrlPermission/UrlPermissions/defaults.py
UrlPermission/UrlPermissions/settings.py
UrlPermission/UrlPermissions/urls.py
UrlPermission/UrlPermissions/wsgi.py
UrlPermission/permissions/__init__.py
UrlPermission/permissions/admin.py
UrlPermission/permissions/app.py
UrlPermission/permissions/defaults.py
UrlPermission/permissions/extras.py
UrlPermission/permissions/forms.py
UrlPermission/permissions/middlewares.py
UrlPermission/permissions/models.py
UrlPermission/permissions/urls.py
UrlPermission/permissions/utils.py
UrlPermission/permissions/views.py
UrlPermission/permissions/migrations/0001_initial.py
UrlPermission/permissions/migrations/__init__.py
UrlPermissions/__init__.py
UrlPermissions/asgi.py
UrlPermissions/defaults.py
UrlPermissions/settings.py
UrlPermissions/urls.py
UrlPermissions/wsgi.py
permissions/__init__.py
permissions/app.py
permissions/extras.py
permissions/forms.py
permissions/middlewares.py
permissions/models.py
permissions/urls.py
permissions/utils.py
permissions/views.py
permissions/migrations/0001_initial.py
permissions/migrations/__init__.py
django_url_permissions-0.2.1.dist-info/LICENSE
django_url_permissions-0.2.1.dist-info/METADATA
django_url_permissions-0.2.1.dist-info/WHEEL
django_url_permissions-0.2.1.dist-info/top_level.txt
django_url_permissions-0.2.1.dist-info/RECORD
