Metadata-Version: 2.1
Name: django-url-permissions
Version: 0.2.1
Summary: A Django app to give role permissions on urls directly.
Home-page: https://github.com/yazanpsut/django-url-permissions
Author: Yazan Alhorani
Author-email: yazan.alhorani@gmail.com
License: MIT
Platform: UNKNOWN
Classifier: Environment :: Web Environment
Classifier: Framework :: Django
Classifier: Framework :: Django :: 3.0
Classifier: Intended Audience :: Developers
Classifier: License :: OSI Approved :: MIT License
Classifier: Operating System :: OS Independent
Classifier: Programming Language :: Python
Classifier: Programming Language :: Python :: 3
Classifier: Programming Language :: Python :: 3.6
Classifier: Topic :: Internet :: WWW/HTTP
Classifier: Topic :: Internet :: WWW/HTTP :: Dynamic Content
